setup.py
slicematrixIO/__init__.py
slicematrixIO/bayesian_filters.py
slicematrixIO/classifiers.py
slicematrixIO/client.py
slicematrixIO/connect.py
slicematrixIO/core.py
slicematrixIO/distributions.py
slicematrixIO/graphs.py
slicematrixIO/manifolds.py
slicematrixIO/matrices.py
slicematrixIO/matrix_models.py
slicematrixIO/notebook.py
slicematrixIO/regressors.py
slicematrixIO/utils.py
slicematrixIO.egg-info/PKG-INFO
slicematrixIO.egg-info/SOURCES.txt
slicematrixIO.egg-info/dependency_links.txt
slicematrixIO.egg-info/not-zip-safe
slicematrixIO.egg-info/requires.txt
slicematrixIO.egg-info/top_level.txt