Metadata-Version: 1.0
Name: slicematrixIO
Version: 0.1.8
Summary: SliceMatrix-IO Python API
Home-page: http://www.slicematrix.io
Author: Hekaton LLC
Author-email: tynan@slicematrix.com
License: MIT
Platform: UNKNOWN
